anvilrl/__init__.py
anvilrl/agents/__init__.py
anvilrl/agents/a2c.py
anvilrl/agents/base_agents.py
anvilrl/agents/ddpg.py
anvilrl/agents/dqn.py
anvilrl/agents/es.py
anvilrl/agents/ga.py
anvilrl/agents/templates.py
anvilrl/buffers/__init__.py
anvilrl/buffers/base_buffer.py
anvilrl/buffers/her_buffer.py
anvilrl/buffers/replay_buffer.py
anvilrl/buffers/rollout_buffer.py
anvilrl/callbacks/__init__.py
anvilrl/callbacks/base_callback.py
anvilrl/callbacks/checkpoint_callback.py
anvilrl/common/enumerations.py
anvilrl/common/logging_.py
anvilrl/common/type_aliases.py
anvilrl/common/utils.py
anvilrl/demo.py
anvilrl/explorers/__init__.py
anvilrl/explorers/base_explorer.py
anvilrl/explorers/gaussian_explorer.py
anvilrl/models/__init__.py
anvilrl/models/actor_critics.py
anvilrl/models/encoders.py
anvilrl/models/heads.py
anvilrl/models/torsos.py
anvilrl/models/utils.py
anvilrl/plot.py
anvilrl/settings.py
anvilrl/signal_processing/__init__.py
anvilrl/signal_processing/advantage_estimators.py
anvilrl/signal_processing/crossover_operators.py
anvilrl/signal_processing/mutation_operators.py
anvilrl/signal_processing/return_estimators.py
anvilrl/signal_processing/sample_estimators.py
anvilrl/signal_processing/selection_operators.py
anvilrl/updaters/__init__.py
anvilrl/updaters/actors.py
anvilrl/updaters/critics.py
anvilrl/updaters/evolution.py
anvilrl-0.4.0.dist-info/LICENSE
anvilrl-0.4.0.dist-info/WHEEL
anvilrl-0.4.0.dist-info/METADATA
anvilrl-0.4.0.dist-info/RECORD
